pyfatsecret/__init__.py
pyfatsecret/autogen.py
pyfatsecret/fatsecret.py
pyfatsecret/fatsecret_base.py
pyfatsecret/foods.py
pyfatsecret/profile_auth.py
pyfatsecret/profile_exercise_diary.py
pyfatsecret/profile_food_diary.py
pyfatsecret/profile_foods.py
pyfatsecret/profile_recipes.py
pyfatsecret/profile_saved_meals.py
pyfatsecret/profile_weight_diary.py
pyfatsecret/recipes.py
pyfatsecret-0.1.1.dist-info/LICENSE
pyfatsecret-0.1.1.dist-info/METADATA
pyfatsecret-0.1.1.dist-info/WHEEL
pyfatsecret-0.1.1.dist-info/top_level.txt
pyfatsecret-0.1.1.dist-info/RECORD
