Metadata-Version: 2.1
Name: pyfatsecret
Version: 0.1.1
Summary: A simple python wrapper for the Fatsecret API.
Home-page: https://https://github.com/misrolox/pyfatsecret
Author: Andrew Mitri
Author-email: mitriandrew@hotmail.com
License: MIT
Classifier: Programming Language :: Python :: 3
Classifier: License :: OSI Approved :: MIT License
Classifier: Operating System :: OS Independent
Requires-Python: >=3.10
License-File: LICENSE
Requires-Dist: requests ==2.31.0
